text2midi.py
text2midi-0.0.1.dist-info/LICENSE
text2midi-0.0.1.dist-info/WHEEL
text2midi-0.0.1.dist-info/METADATA
text2midi-0.0.1.dist-info/RECORD
