Metadata-Version: 2.1
Name: text2midi
Version: 0.0.1
Summary: text2midi
Home-page: https://github.com/nshdesai/text2midi
Author: Nishkrit Desai
Author-email: nishkritdesai10@gmail.com
Classifier: License :: OSI Approved :: MIT License
